setup.py
scripts/cloudp
src/mycloud/__init__.py
src/mycloud/cluster.py
src/mycloud/config.py
src/mycloud/connections.py
src/mycloud/fs.py
src/mycloud/mapreduce.py
src/mycloud/resource.py
src/mycloud/thread.py
src/mycloud/util.py
src/mycloud/worker.py
src/mycloud/worker_main.py
src/mycloud.egg-info/PKG-INFO
src/mycloud.egg-info/SOURCES.txt
src/mycloud.egg-info/dependency_links.txt
src/mycloud.egg-info/requires.txt
src/mycloud.egg-info/top_level.txt